<?xml version="1.0" encoding="UTF-8"?>
<feature
      id="org.eclipse.actf.visualization.sdk"
      label="ACTF Visualization SDK Feature (Incubation)"
      version="0.8.2.R201102161930"
      provider-name="Eclipse.org"
      os="win32"
      ws="win32"
      arch="x86">

   <description>
      %description
   </description>

   <copyright>
      %copyright
   </copyright>

   <license url="license.html">
      %license
   </license>

   <url>
      <update label="Eclipse ACTF Update Site" url="http://download.eclipse.org/technology/actf/0.8/update-site/"/>
   </url>

   <includes
         id="org.eclipse.actf.visualization.source"
         version="0.8.2.R201102161930"/>

   <includes
         id="org.eclipse.actf.visualization"
         version="0.8.2.R201102161930"/>

   <plugin
         id="org.eclipse.actf.visualization.doc.isv"
         download-size="0"
         install-size="0"
         version="0.8.2.R201102161930"
         unpack="false"/>

   <plugin
         id="org.eclipse.actf.visualization.sdk"
         download-size="0"
         install-size="0"
         version="0.8.2.R201102161930"/>

</feature>
